oscar_invoices/__init__.py
oscar_invoices/abstract_models.py
oscar_invoices/admin.py
oscar_invoices/app_settings.py
oscar_invoices/apps.py
oscar_invoices/models.py
oscar_invoices/storages.py
oscar_invoices/urls.py
oscar_invoices/utils.py
oscar_invoices/views.py
oscar_invoices/locale/en/LC_MESSAGES/django.mo
oscar_invoices/locale/en/LC_MESSAGES/django.po
oscar_invoices/locale/nl/LC_MESSAGES/django.mo
oscar_invoices/locale/nl/LC_MESSAGES/django.po
oscar_invoices/migrations/0001_initial.py
oscar_invoices/migrations/0002_auto_20180822_1335.py
oscar_invoices/migrations/0003_auto_20190403_1910.py
oscar_invoices/migrations/__init__.py
oscar_invoices/templates/oscar_invoices/invoice.html
django_oscar_invoices-0.2.dist-info/METADATA
django_oscar_invoices-0.2.dist-info/WHEEL
django_oscar_invoices-0.2.dist-info/top_level.txt
django_oscar_invoices-0.2.dist-info/RECORD
