Metadata-Version: 2.1
Name: django-oscar-invoices
Version: 0.2
Summary: Invoices generation for Django Oscar
Home-page: https://github.com/django-oscar/django-oscar-invoices
Author: Metaclass Team
Author-email: sasha@metaclass.co
License: BSD
Platform: UNKNOWN
Classifier: Development Status :: 4 - Beta
Classifier: Environment :: Web Environment
Classifier: Framework :: Django
Classifier: Framework :: Django :: 2.0
Classifier: Intended Audience :: Developers
Classifier: License :: OSI Approved :: BSD License
Classifier: Operating System :: Unix
Classifier: Programming Language :: Python :: 3
Classifier: Programming Language :: Python :: 3.5
Classifier: Programming Language :: Python :: 3.6
Requires-Dist: psycopg2-binary (<2.9,>=2.8)
Requires-Dist: phonenumbers
Requires-Dist: pillow
Requires-Dist: django (<2.3,>=1.11)
Requires-Dist: django-oscar (>=2.0)
Requires-Dist: django-phonenumber-field (<4.0.0,>=3.0.0)
Provides-Extra: test
Requires-Dist: pytest (>=3.6.0) ; extra == 'test'
Requires-Dist: pytest-django ; extra == 'test'
Requires-Dist: django-webtest (==1.9.3) ; extra == 'test'
